tigris_python_sdk-0.1.7.dist-info/DESCRIPTION.rst
tigris_python_sdk-0.1.7.dist-info/METADATA
tigris_python_sdk-0.1.7.dist-info/RECORD
tigris_python_sdk-0.1.7.dist-info/WHEEL
tigris_python_sdk-0.1.7.dist-info/metadata.json
tigris_python_sdk-0.1.7.dist-info/top_level.txt
tigrissdk/__init__.py
tigrissdk/base_object.py
tigrissdk/config.py
tigrissdk/exception.py
tigrissdk/version.py
tigrissdk/auth/__init__.py
tigrissdk/auth/permission.py
tigrissdk/auth/role.py
tigrissdk/auth/user.py
tigrissdk/client/__init__.py
tigrissdk/notification/__init__.py
tigrissdk/platform/__init__.py
tigrissdk/platform/assessment.py
tigrissdk/platform/course.py
tigrissdk/platform/enrollment.py
tigrissdk/platform/module.py
tigrissdk/service/__init__.py
tigrissdk/session/__init__.py
tigrissdk/session/tigris_auth_session.py
tigrissdk/session/tigris_session.py
tigrissdk/util/__init__.py
