Metadata-Version: 2.0
Name: tigris-python-sdk
Version: 0.1.7
Summary: The official Python SDK for Jogral Tigris
Home-page: https://labs.jogral.co/
Author: Jogral, L.L.C.
Author-email: code@jogral.io
License: Apache Public License 2.0
Keywords: jogral tigris learning sdk
Platform: UNKNOWN
Classifier: Development Status :: 4 - Beta
Classifier: Programming Language :: Python :: Implementation :: CPython
Classifier: Operating System :: OS Independent
Classifier: Operating System :: POSIX
Classifier: Operating System :: Microsoft :: Windows
Classifier: Operating System :: MacOS :: MacOS X
Classifier: Environment :: Other Environment
Classifier: Topic :: Software Development :: Libraries :: Python Modules
Classifier: Intended Audience :: Developers
Requires-Dist: py (>=1.4.29)
Requires-Dist: setuptools
Requires-Dist: certifi (==2017.7.27.1)
Requires-Dist: chardet (==3.0.4)
Requires-Dist: idna (==2.6)
Requires-Dist: requests (==2.18.4)
Requires-Dist: urllib3 (==1.22)
Requires-Dist: argparse; python_version=="2.6"
Requires-Dist: colorama; sys_platform=="win32"
